{
  "$schema": "http://json-schema.org/draft-04/schema#",
  "id": "KBV_PR_FOR_Coverage",
  "oneOf": [
    {
      "$ref": "#/definitions/KBV_PR_FOR_Coverage"
    }
  ],
  "definitions": {
    "KBV_PR_FOR_Coverage": {
      "properties": {
        "resourceType": {
          "enum": [
            "Coverage"
          ]
        },
        "id": {
          "$ref": "../BaseSchema.json#/definitions/id"
        },
        "meta": {
          "$ref": "#/definitions/Coverage_Meta"
        },
        "extension": {
          "type": "array",
          "maxItems": 4,
          "uniqueItems": true,
          "items": {
            "anyOf": [
              {
                "$ref": "KennzeichenWohnortprinzip.json#/definitions/KennzeichenWohnortprinzip"
              },
              {
                "$ref": "VersichertenartGKV.json#/definitions/VersichertenartGKV"
              },
              {
                "$ref": "ExtensionGkvDmpKennzeichen.json#/definitions/ExtensionGkvDmpKennzeichen"
              },
              {
                "$ref": "ExtensionGkvBesonderePersonengruppe.json#/definitions/ExtensionGkvBesonderePersonengruppe"
              }
            ]
          },
          "additionalItems": false
        },
        "modifierExtension": {
          "items": {
            "$ref": "../BaseSchema.json#/definitions/Extension"
          },
          "type": "array"
        },
        "status": {
          "enum": [
            "active"
          ]
        },
        "_status": {
          "$ref": "../BaseSchema.json#/definitions/Element"
        },
        "type": {
          "$ref": "#/definitions/Coverage_CodeableConcept"
        },
        "beneficiary": {
          "$ref": "#/definitions/beneficiary_Reference"
        },
        "period": {
          "$ref": "#/definitions/Coverage_Period"
        },
        "payor": {
          "type": "array",
          "minItems": 1,
          "maxItems": 1,
          "items": {
            "$ref": "#/definitions/payor_Reference"
          }
        }
      },
      "additionalProperties": false,
      "required": [
        "resourceType",
        "id",
        "meta",
        "status",
        "type",
        "beneficiary",
        "payor"
      ]
    },
    "Coverage_Class": {
      "properties": {
        "id": {
          "$ref": "../BaseSchema.json#/definitions/string"
        },
        "extension": {
          "items": {
            "$ref": "../BaseSchema.json#/definitions/Extension"
          },
          "type": "array"
        },
        "modifierExtension": {
          "items": {
            "$ref": "../BaseSchema.json#/definitions/Extension"
          },
          "type": "array"
        },
        "type": {
          "$ref": "../BaseSchema.json#/definitions/CodeableConcept"
        },
        "value": {
          "$ref": "../BaseSchema.json#/definitions/string"
        },
        "_value": {
          "$ref": "../BaseSchema.json#/definitions/Element"
        },
        "name": {
          "$ref": "../BaseSchema.json#/definitions/string"
        },
        "_name": {
          "$ref": "../BaseSchema.json#/definitions/Element"
        }
      },
      "additionalProperties": false,
      "required": [
        "type"
      ]
    },
    "Coverage_CostToBeneficiary": {
      "properties": {
        "id": {
          "$ref": "../BaseSchema.json#/definitions/string"
        },
        "extension": {
          "items": {
            "$ref": "../BaseSchema.json#/definitions/Extension"
          },
          "type": "array"
        },
        "modifierExtension": {
          "items": {
            "$ref": "../BaseSchema.json#/definitions/Extension"
          },
          "type": "array"
        },
        "type": {
          "$ref": "../BaseSchema.json#/definitions/CodeableConcept"
        },
        "valueQuantity": {
          "$ref": "../BaseSchema.json#/definitions/Quantity"
        },
        "valueMoney": {
          "$ref": "../BaseSchema.json#/definitions/Money"
        },
        "exception": {
          "items": {
            "$ref": "#/definitions/Coverage_Exception"
          },
          "type": "array"
        }
      },
      "additionalProperties": false
    },
    "Coverage_Exception": {
      "properties": {
        "id": {
          "$ref": "../BaseSchema.json#/definitions/string"
        },
        "extension": {
          "items": {
            "$ref": "../BaseSchema.json#/definitions/Extension"
          },
          "type": "array"
        },
        "modifierExtension": {
          "items": {
            "$ref": "../BaseSchema.json#/definitions/Extension"
          },
          "type": "array"
        },
        "type": {
          "$ref": "../BaseSchema.json#/definitions/CodeableConcept"
        },
        "period": {
          "$ref": "../BaseSchema.json#/definitions/Period"
        }
      },
      "additionalProperties": false,
      "required": [
        "type"
      ]
    },
    "Coverage_Meta": {
      "properties": {
        "id": {
          "$ref": "../BaseSchema.json#/definitions/string"
        },
        "extension": {
          "items": {
            "$ref": "../BaseSchema.json#/definitions/Extension"
          },
          "type": "array"
        },
        "profile": {
          "type": "array",
          "minItems": 1,
          "maxItems": 1,
          "items": {
            "enum": [
              "https://fhir.kbv.de/StructureDefinition/KBV_PR_FOR_Coverage|1.0.3"
            ]
          }
        }
      },
      "additionalProperties": false,
      "required": [
        "profile"
      ]
    },
    "Coverage_CodeableConcept": {
      "properties": {
        "id": {
          "$ref": "../BaseSchema.json#/definitions/string"
        },
        "extension": {
          "items": {
            "$ref": "../BaseSchema.json#/definitions/Extension"
          },
          "type": "array"
        },
        "coding": {
          "type": "array",
          "minItems": 1,
          "maxItems": 1,
          "items": {
            "$ref": "#/definitions/Coverage_CodeableConcept_Coding"
          }
        }
      },
      "additionalProperties": false,
      "required": [
        "coding"
      ]
    },
    "Coverage_CodeableConcept_Coding": {
      "properties": {
        "id": {
          "$ref": "../BaseSchema.json#/definitions/string"
        },
        "extension": {
          "items": {
            "$ref": "../BaseSchema.json#/definitions/Extension"
          },
          "type": "array"
        },
        "system": {
          "enum": [
            "http://fhir.de/CodeSystem/versicherungsart-de-basis",
            "https://fhir.kbv.de/CodeSystem/KBV_CS_FOR_Payor_Type_KBV"
          ]
        },
        "_system": {
          "$ref": "../BaseSchema.json#/definitions/Element"
        },
        "code": {
          "enum": [
            "GKV",
            "PKV",
            "BG",
            "SEL"
          ]
        },
        "_code": {
          "$ref": "../BaseSchema.json#/definitions/Element"
        }
      },
      "additionalProperties": false,
      "required": [
        "system",
        "code"
      ]
    },
    "beneficiary_Reference": {
      "properties": {
        "id": {
          "$ref": "../BaseSchema.json#/definitions/string"
        },
        "extension": {
          "items": {
            "$ref": "../BaseSchema.json#/definitions/Extension"
          },
          "type": "array"
        },
        "reference": {
          "$ref": "../BaseSchema.json#/definitions/string"
        },
        "_reference": {
          "$ref": "../BaseSchema.json#/definitions/Element"
        }
      },
      "additionalProperties": false,
      "required": [
        "reference"
      ]
    },
    "Coverage_Period": {
      "properties": {
        "id": {
          "$ref": "../BaseSchema.json#/definitions/string"
        },
        "extension": {
          "items": {
            "$ref": "../BaseSchema.json#/definitions/Extension"
          },
          "type": "array"
        },
        "end": {
          "$ref": "../BaseSchema.json#/definitions/dateTime"
        },
        "_end": {
          "$ref": "../BaseSchema.json#/definitions/Element"
        }
      },
      "additionalProperties": false,
      "required": [
        "end"
      ]
    },
    "payor_Reference": {
      "properties": {
        "id": {
          "$ref": "../BaseSchema.json#/definitions/string"
        },
        "extension": {
          "items": {
            "$ref": "../BaseSchema.json#/definitions/Extension"
          },
          "type": "array"
        },
        "identifier": {
          "$ref": "#/definitions/IKNR"
        },
        "display": {
          "$ref": "../BaseSchema.json#/definitions/string"
        },
        "_display": {
          "$ref": "../BaseSchema.json#/definitions/Element"
        }
      },
      "additionalProperties": false,
      "required": [
        "display"
      ]
    },
    "IKNR": {
      "properties": {
        "id": {
          "$ref": "../BaseSchema.json#/definitions/string"
        },
        "extension": {
          "type": "array",
          "maxItems": 1,
          "items": {
            "$ref": "#/definitions/alternativeID"
          },
          "additionalItems": false
        },
        "use": {
          "enum": [
            "official"
          ]
        },
        "_use": {
          "$ref": "../BaseSchema.json#/definitions/Element"
        },
        "type": {
          "$ref": "#/definitions/XX-Type_CodeableConcept"
        },
        "system": {
          "enum": [
            "http://fhir.de/NamingSystem/arge-ik/iknr"
          ]
        },
        "_system": {
          "$ref": "../BaseSchema.json#/definitions/Element"
        },
        "value": {
          "$ref": "../BaseSchema.json#/definitions/string"
        },
        "_value": {
          "$ref": "../BaseSchema.json#/definitions/Element"
        }
      },
      "additionalProperties": false,
      "required": [
        "system",
        "value"
      ]
    },
    "alternativeID": {
      "properties": {
        "id": {
          "$ref": "../BaseSchema.json#/definitions/string"
        },
        "extension": {
          "items": {
            "$ref": "../BaseSchema.json#/definitions/Extension"
          },
          "type": "array"
        },
        "url": {
          "enum": [
            "https://fhir.kbv.de/StructureDefinition/KBV_EX_FOR_Alternative_IK"
          ]
        },
        "_url": {
          "$ref": "../BaseSchema.json#/definitions/Element"
        },
        "valueIdentifier": {
          "$ref": "#/definitions/alternativeID_Identifier"
        }
      },
      "additionalProperties": false,
      "required": [
        "url",
        "valueIdentifier"
      ]
    },
    "alternativeID_Identifier": {
      "properties": {
        "id": {
          "$ref": "../BaseSchema.json#/definitions/string"
        },
        "extension": {
          "items": {
            "$ref": "../BaseSchema.json#/definitions/Extension"
          },
          "type": "array"
        },
        "use": {
          "enum": [
            "official"
          ]
        },
        "_use": {
          "$ref": "../BaseSchema.json#/definitions/Element"
        },
        "type": {
          "$ref": "#/definitions/XX-Type_CodeableConcept"
        },
        "system": {
          "enum": [
            "http://fhir.de/NamingSystem/arge-ik/iknr"
          ]
        },
        "_system": {
          "$ref": "../BaseSchema.json#/definitions/Element"
        },
        "value": {
          "type": "string",
          "pattern": "^\\d{9}$"
        },
        "_value": {
          "$ref": "../BaseSchema.json#/definitions/Element"
        }
      },
      "additionalProperties": false,
      "required": [
        "system",
        "value"
      ]
    },
    "XX-Type_CodeableConcept": {
      "properties": {
        "id": {
          "$ref": "../BaseSchema.json#/definitions/string"
        },
        "extension": {
          "items": {
            "$ref": "../BaseSchema.json#/definitions/Extension"
          },
          "type": "array"
        },
        "XX-Type": {
          "type": "array",
          "items": {
            "$ref": "#/definitions/XX-Type_Coding"
          }
        }
      },
      "additionalProperties": false
    },
    "XX-Type_Coding": {
      "properties": {
        "id": {
          "$ref": "../BaseSchema.json#/definitions/string"
        },
        "extension": {
          "items": {
            "$ref": "../BaseSchema.json#/definitions/Extension"
          },
          "type": "array"
        },
        "system": {
          "$ref": "../BaseSchema.json#/definitions/uri"
        },
        "_system": {
          "$ref": "../BaseSchema.json#/definitions/Element"
        },
        "code": {
          "$ref": "../BaseSchema.json#/definitions/code"
        },
        "_code": {
          "$ref": "../BaseSchema.json#/definitions/Element"
        }
      },
      "additionalProperties": false
    }
  }
}
